{
    "N/R/U": null,
    "Applicant": "Iso-Tex Diagnostics, Inc. ",
    "BLA Number": "17837",
    "Proprietary Name": "Megatope",
    "Proper Name": "iodinated I-131 albumin",
    "BLA Type": "351(a)",
    "Strength": "5uCi/AMP",
    "Dosage Form": "Injection ",
    "Route of Administration": "Intravenous",
    "Product Presentation": "Multi-Dose Vial",
    "Marketing Status": "Disc",
    "Licensure": "Licensed",
    "Approval Date": "23-Feb-76",
    "Ref. Product Proper Name": null,
    "Ref. Product Proprietary Name": null,
    "Supplement Number": null,
    "Submission Type": "Original",
    "License Number": "2189",
    "Product Number": "4",
    "Center": "CDER",
    "Date of First Licensure": null,
    "Exclusivity Expiration Date": null,
    "First Interchangeable Exclusivity Exp. Date": null,
    "Ref. Product Exclusivity Exp. Date": null,
    "Orphan Exclusivity Exp. Date": null
}