{
    "Ingredient": "SULFAMETHOXAZOLE; TRIMETHOPRIM",
    "DF;Route": "SUSPENSION;ORAL",
    "Trade_Name": "SEPTRA GRAPE",
    "Applicant": "MONARCH PHARMS",
    "Strength": "200MG/5ML;40MG/5ML **Federal Register determination that product was not discontinued or withdrawn for safety or effectiveness reasons**",
    "Appl_Type": "N",
    "Appl_No": 17598,
    "Product_No": 2,
    "TE_Code": null,
    "Approval_Date": "Feb 12, 1986",
    "RLD": "No",
    "RS": "No",
    "Type": "DISCN",
    "Applicant_Full_Name": "MONARCH PHARMACEUTICALS INC"
}